setup.py
myvariant/__init__.py
myvariant/api.py
myvariant/metadata.py
myvariant/variant.py
myvariant_api.egg-info/PKG-INFO
myvariant_api.egg-info/SOURCES.txt
myvariant_api.egg-info/dependency_links.txt
myvariant_api.egg-info/requires.txt
myvariant_api.egg-info/top_level.txt
tests/metadata_test.py
tests/sample.py
tests/variant_test.py