Metadata-Version: 1.0
Name: myvariant-api
Version: 1.0
Summary: A simple API wrapper for the MyVariant.info API.
Home-page: UNKNOWN
Author: Brian Schrader
Author-email: brian@biteofanapple.com
License: LICENSE.txt
Keywords: variant,genomics
Platform: UNKNOWN
